pollination_io/__init__.py
pollination_io/dataframe.py
pollination_io/interactors.py
pollination_io/api/__init__.py
pollination_io/api/_base.py
pollination_io/api/client.py
pollination_io/api/jobs.py
pollination_io/api/recipes.py
pollination_io/api/runs.py
pollination_io/api/user.py
pollination_io-1.1.1.dist-info/LICENSE
pollination_io-1.1.1.dist-info/METADATA
pollination_io-1.1.1.dist-info/WHEEL
pollination_io-1.1.1.dist-info/top_level.txt
pollination_io-1.1.1.dist-info/RECORD
