Metadata-Version: 2.1
Name: pollination-io
Version: 1.1.1
Summary: A Pollination extension to facilitate working with Pollination SDK.
Home-page: https://github.com/pollination/pollination-io
Author: Pollination
Author-email: info@pollination.solutions
License: Apache-2.0 License
Platform: UNKNOWN
Classifier: Programming Language :: Python :: 3.10
Classifier: Programming Language :: Python :: Implementation :: CPython
Classifier: License :: OSI Approved :: Apache Software License
Classifier: Operating System :: OS Independent
License-File: LICENSE
Requires-Dist: requests
Requires-Dist: queenbee
Requires-Dist: pandas (>=1.3.5)
Requires-Dist: numpy (<2.0.0)
